kaitian/__about__.py
kaitian/__init__.py
kaitian/analyzer/__init__.py
kaitian/analyzer/calculator.py
kaitian/analyzer/evaluator.py
kaitian/analyzer/selector.py
kaitian/plotter/__init__.py
kaitian/plotter/distribution_plot.py
kaitian/plotter/linebar_plot.py
kaitian/plotter/static/LXGWNeoXiHeiPlus.ttf
kaitian/plotter/static/__init__.py
kaitian/plotter/static/theme_nature.json
kaitian/plotter/static/theme_purple.json
kaitian/plotter/static/theme_science.json
kaitian/plotter/static/theme_sharp.json
kaitian/plotter/themer.py
kaitian/preprocessor/__init__.py
kaitian/preprocessor/__proto__.py
kaitian/preprocessor/binner.py
kaitian/preprocessor/encoder.py
kaitian/py.typed
kaitian/trainer/__init__.py
kaitian/trainer/__proto__.py
kaitian/trainer/lightgbm.py
kaitian/utils/__init__.py
kaitian/utils/excel.py
kaitian/utils/logger.py
kaitian/utils/plextras.py
kaitian/utils/scanner.py
kaitian-0.7.0.dist-info/WHEEL
kaitian-0.7.0.dist-info/METADATA
kaitian-0.7.0.dist-info/RECORD
