Metadata-Version: 2.3
Name: kaitian
Version: 0.7.0
Summary: Statistical learning tools for data science modeling engineer.
Author: ashswing
Author-email: ashswing <ashswing@email.cn>
Requires-Dist: cryptography>=46.0.3
Requires-Dist: fastexcel>=0.12.1
Requires-Dist: matplotlib>=3.7.5
Requires-Dist: numba>=0.58.1
Requires-Dist: numpy>=1.24.4
Requires-Dist: openpyxl>=3.1.5
Requires-Dist: optuna>=4.5.0
Requires-Dist: polars>=1.8.2
Requires-Dist: psutil>=7.1.1
Requires-Dist: pyarrow>=17.0.0
Requires-Dist: scikit-learn>=1.3.2
Requires-Dist: scipy>=1.10.1
Requires-Dist: typing-extensions>=4.13.2
Requires-Dist: xlsxwriter>=3.2.9
Requires-Dist: kaitian[gbdt,gbdt-plus,pretty,app] ; extra == 'all'
Requires-Dist: click>=8.1.8 ; extra == 'app'
Requires-Dist: lightgbm>=4.6.0 ; extra == 'gbdt'
Requires-Dist: xgboost>=2.1.4 ; extra == 'gbdt'
Requires-Dist: catboost>=1.2.8 ; extra == 'gbdt-plus'
Requires-Dist: shap>=0.44.1 ; extra == 'gbdt-plus'
Requires-Dist: rich>=14.2.0 ; extra == 'pretty'
Requires-Dist: ipywidgets>=8.1.7 ; extra == 'pretty'
Requires-Dist: great-tables>=0.17 ; python_full_version >= '3.9' and extra == 'pretty'
Requires-Dist: great-tables~=0.2.0 ; python_full_version < '3.9' and extra == 'pretty'
Requires-Python: >=3.8, <3.13
Provides-Extra: all
Provides-Extra: app
Provides-Extra: gbdt
Provides-Extra: gbdt-plus
Provides-Extra: pretty
